mysql_mcp_xu/.env
mysql_mcp_xu/__init__.py
mysql_mcp_xu/config.py
mysql_mcp_xu/db_conn.py
mysql_mcp_xu/mcp_server.py
mysql_mcp_xu-0.1.9.dist-info/METADATA
mysql_mcp_xu-0.1.9.dist-info/WHEEL
mysql_mcp_xu-0.1.9.dist-info/entry_points.txt
mysql_mcp_xu-0.1.9.dist-info/licenses/LICENSE
mysql_mcp_xu-0.1.9.dist-info/RECORD
