Metadata-Version: 2.4
Name: mysql-mcp-xu
Version: 0.1.9
Summary: 使用FastMCP构建MySql Mcp Server，支持Streamable HTTP, STDIO, SSE，支持读写权限控制
Project-URL: repository, https://github.com/XMQSVIP/mysql-mcp-xu
Author-email: xmq <xmqsvip@qq.com>
License-File: LICENSE
Keywords: mcp,mcp-server,mysql
Requires-Python: >=3.10
Requires-Dist: aiomysql>=0.2.0
Requires-Dist: fastmcp>=2.7.1
Requires-Dist: python-dotenv>=1.1.0
